mapy/__init__.py
mapy/constants.py
mapy/fem.py
mapy/version.py
mapy/integrate/__init__.py
mapy/integrate/test_trapz2d_simps2d.py
mapy/model/__init__.py
mapy/model/coords.py
mapy/model/grids.py
mapy/model/rebuild.py
mapy/model/constraints/__init__.py
mapy/model/elements/__init__.py
mapy/model/elements/derivation_rotation_matrix.py
mapy/model/elements/elem1d.py
mapy/model/elements/elem2d.py
mapy/model/elements/elem3d.py
mapy/model/elements/elembar.py
mapy/model/elements/elemquad4.py
mapy/model/elements/elemrod.py
mapy/model/elements/gauss_legendre.py
mapy/model/elements/elemquad/__init__.py
mapy/model/elements/elemtria/__init__.py
mapy/model/elements/elemtria/cst_equations.py
mapy/model/elements/elemtria/elemtria3.py
mapy/model/loads/__init__.py
mapy/model/loads/loads.py
mapy/model/loads/subcases.py
mapy/model/materials/__init__.py
mapy/model/materials/matiso.py
mapy/model/materials/matlamina.py
mapy/model/properties/__init__.py
mapy/model/properties/prop1d.py
mapy/model/properties/prop2d.py
mapy/model/properties/composite/__init__.py
mapy/model/properties/composite/lamina.py
mapy/model/properties/composite/laminate.py
mapy/model/properties/composite/pcomp.py
mapy/modgen/__init__.py
mapy/modgen/cylinder/__init__.py
mapy/mplutils/__init__.py
mapy/mplutils/_big.py
mapy/mplutils/_small.py
mapy/mplutils/input_from_txt.py
mapy/mplutils/plot_defaults.py
mapy/reader/__init__.py
mapy/reader/cardtranslator.py
mapy/reader/input_reader.py
mapy/renderer/__init__.py
mapy/solver/__init__.py
mapy/solver/solver.py
mapy/sympytools/__init__.py
mapy/sympytools/denominator.py
mapy/sympytools/doperator.py
mapy/sympytools/mathematica_printer.py
mapy/sympytools/matrixtools.py
mapy/sympytools/voperator.py
mapy/sympytools/voperator2.py
mapy/writer/__init__.py
mapy/writer/abaqus.py
mapy_package-0.15.0.dist-info/DESCRIPTION.rst
mapy_package-0.15.0.dist-info/METADATA
mapy_package-0.15.0.dist-info/RECORD
mapy_package-0.15.0.dist-info/WHEEL
mapy_package-0.15.0.dist-info/metadata.json
mapy_package-0.15.0.dist-info/top_level.txt
