Metadata-Version: 2.0
Name: mapy-package
Version: 0.15.0
Summary: Modeling and Analysis in Python
Home-page: https://github.com/saullocastro/mapy
Author: Saullo G. P. Castro
Author-email: castrosaullo@gmail.com
License: BSD
Keywords: finite element modeling analysis
Platform: UNKNOWN
Classifier: Development Status :: 3 - Alpha
Classifier: Topic :: Scientific/Engineering :: Mathematics
Classifier: License :: OSI Approved :: BSD License
Requires-Dist: alg3dpy
